adafruit_dacx578.py
adafruit_circuitpython_dacx578-1.0.1.dist-info/licenses/LICENSE
adafruit_circuitpython_dacx578-1.0.1.dist-info/METADATA
adafruit_circuitpython_dacx578-1.0.1.dist-info/WHEEL
adafruit_circuitpython_dacx578-1.0.1.dist-info/top_level.txt
adafruit_circuitpython_dacx578-1.0.1.dist-info/RECORD
