Metadata-Version: 2.4
Name: adafruit-circuitpython-dacx578
Version: 1.0.1
Summary: CircuitPython driver for the Adafruit DAC7578 - 8 x Channel 12-bit I2C DAC - STEMMA QT / Qwiic
Author-email: Adafruit Industries <circuitpython@adafruit.com>
License: MIT
Project-URL: Homepage, https://github.com/adafruit/Adafruit_CircuitPython_DACx578
Keywords: adafruit,blinka,circuitpython,micropython,dacx578,DAC,,12-bit
Classifier: Intended Audience :: Developers
Classifier: Topic :: Software Development :: Libraries
Classifier: Topic :: Software Development :: Embedded Systems
Classifier: Topic :: System :: Hardware
Classifier: License :: OSI Approved :: MIT License
Classifier: Programming Language :: Python :: 3
License-File: LICENSE
Requires-Dist: Adafruit-Blinka
Requires-Dist: adafruit-circuitpython-busdevice
Provides-Extra: optional
Dynamic: license-file
